alumathpeergroup9/__init__.py
alumathpeergroup9/matrix_ops.py
alumathpeergroup9-0.1.0.dist-info/licenses/LICENSE
alumathpeergroup9-0.1.0.dist-info/METADATA
alumathpeergroup9-0.1.0.dist-info/WHEEL
alumathpeergroup9-0.1.0.dist-info/top_level.txt
alumathpeergroup9-0.1.0.dist-info/RECORD
