Metadata-Version: 2.4
Name: alumathpeergroup9
Version: 0.1.0
Summary: Matrix operations library for Peer-group-9
Author: Peer-group-9
Author-email: 
Classifier: Programming Language :: Python :: 3
Classifier: License :: OSI Approved :: MIT License
Classifier: Operating System :: OS Independent
Requires-Python: >=3.6
License-File: LICENSE
Dynamic: author
Dynamic: classifier
Dynamic: license-file
Dynamic: requires-python
Dynamic: summary
